{
    "plugins": [
        "ga",
        "versions",
        "scripts",
        "edit-link"
    ],
    "title": "NativeBase Market UI Themes",
    "variables":{
      "options": "react-native-flat-app-theme"
       },
    "pluginsConfig": {
      "edit-link": {
            "base": "https://github.com/GeekyAnts/native-base-market-flat-app-docs-ui/tree/master",
            "label": "Edit This Page"
        },
      "scripts": {
          "files": [
              "./engine.js"
          ]
      },
        "versions": {

            "gitbookConfigURL": "http://rawgit.com/GeekyAnts/native-base-market-flat-app-docs-ui/master/book.json",
            "options": [
              {
                  "value": "http://docs.market.nativebase.io/react-native-flat-app-ui",
                  "text": "v6.0.0"
              }
            ]
        },
        "ga": {
            "token": "UA-91837749-1"
        }
    }
}
